typofix/__init__.py
typofix/cli.py
typofix/config.py
typofix/llm.py
typofix/prompts.py
typofix-0.2.0.dist-info/METADATA
typofix-0.2.0.dist-info/WHEEL
typofix-0.2.0.dist-info/entry_points.txt
typofix-0.2.0.dist-info/top_level.txt
typofix-0.2.0.dist-info/RECORD
