Metadata-Version: 2.4
Name: typofix
Version: 0.2.0
Summary: A cross-platform CLI tool to fix typos using LLM.
Requires-Python: >=3.9
Requires-Dist: typer>=0.9.0
Requires-Dist: pyperclip>=1.8.0
Requires-Dist: openai>=1.0.0
